xcmap_bio/__init__.py
xcmap_bio/genome/__init__.py
xcmap_bio/genome/fasta.py
xcmap_bio/genome/gff3.py
xcmap_bio/homology/__init__.py
xcmap_bio/transcriptone/__init__.py
xcmap_bio-0.0.7.dist-info/METADATA
xcmap_bio-0.0.7.dist-info/WHEEL
xcmap_bio-0.0.7.dist-info/RECORD
