Metadata-Version: 2.3
Name: xcmap_bio
Version: 0.0.7
Summary: Biological tools
Author: zhangyang
Author-email: bryanyo1017@126.com
Requires-Python: >=3.13
Classifier: Programming Language :: Python :: 3
Classifier: Programming Language :: Python :: 3.13
Requires-Dist: pandas (>=2.3.2,<3.0.0)
Requires-Dist: pyfaidx (>=0.9.0.3,<0.10.0.0)
Requires-Dist: pysam (>=0.23.3,<0.24.0)
Requires-Dist: xcmap (>=0.1.5,<0.2.0)
